sslogread.cp310-win_amd64.pyd
sslogread-0.8.2.data/data/lib/site-packages/libzstd.dll
sslogread-0.8.2.dist-info/METADATA
sslogread-0.8.2.dist-info/WHEEL
sslogread-0.8.2.dist-info/top_level.txt
sslogread-0.8.2.dist-info/RECORD
